infer_return_type/__init__.py
infer_return_type/generic_utils.py
infer_return_type/infer_return_type.py
infer_return_type-0.1.0.dist-info/METADATA
infer_return_type-0.1.0.dist-info/WHEEL
infer_return_type-0.1.0.dist-info/licenses/LICENSE
infer_return_type-0.1.0.dist-info/RECORD
