Metadata-Version: 2.4
Name: infer-return-type
Version: 0.1.0
Summary: Type inference for generic function return types using formal unification algorithms
Project-URL: Homepage, https://github.com/blackhc/infer-return-type
Project-URL: Repository, https://github.com/blackhc/infer-return-type
Project-URL: Issues, https://github.com/blackhc/infer-return-type/issues
Author-email: Andreas Kirsch <andreas.kirsch@example.com>
License: MIT License
License-File: LICENSE
Keywords: generics,python,type-inference,typing,unification
Classifier: Development Status :: 3 - Alpha
Classifier: Intended Audience :: Developers
Classifier: License :: OSI Approved :: MIT License
Classifier: Programming Language :: Python :: 3
Classifier: Programming Language :: Python :: 3.11
Classifier: Programming Language :: Python :: 3.12
Classifier: Programming Language :: Python :: 3.13
Classifier: Topic :: Software Development :: Libraries :: Python Modules
Classifier: Topic :: Software Development :: Quality Assurance
Classifier: Typing :: Typed
Requires-Python: >=3.11
Requires-Dist: pydantic>=2.11.5
Provides-Extra: dev
Requires-Dist: pytest-cov>=6.0.0; extra == 'dev'
Requires-Dist: pytest>=8.3.5; extra == 'dev'
